{
    "[\"X\",null,\"O\",null,\"O\",null,null,\"X\",null]":{
        "1":{"wins":0,"losses":0},
        "3":{"wins":0,"losses":0},
        "5":{"wins":0,"losses":0},
        "6":{"wins":0,"losses":0},
        "8":{"wins":0,"losses":0}
    },
    "[\"O\",null,null,\"X\",null,null,null,null,null]":{
        "1":{"wins":0,"losses":0},
        "2":{"wins":0,"losses":0},
        "4":{"wins":0,"losses":0},
        "5":{"wins":0,"losses":0},
        "6":{"wins":0,"losses":0},
        "7":{"wins":0,"losses":0},
        "8":{"wins":0,"losses":0}
    },
    "[\"O\",\"X\",\"X\",\"X\",null,null,null,\"O\",\"O\"]":{
        "4":{"wins":0,"losses":0},
        "5":{"wins":0,"losses":0},
        "6":{"wins":0,"losses":0}
    },
    "[null,\"O\",null,\"X\",null,null,null,null,null]":{
        "0":{"wins":0,"losses":0},
        "2":{"wins":0,"losses":0},
        "4":{"wins":0,"losses":0},
        "5":{"wins":0,"losses":0},
        "6":{"wins":0,"losses":0},
        "7":{"wins":0,"losses":0},
        "8":{"wins":0,"losses":0}
    },
    "[\"X\",\"O\",null,\"X\",null,null,\"O\",null,null]":{
        "2":{"wins":0,"losses":0},
        "4":{"wins":0,"losses":0},
        "5":{"wins":0,"losses":0},
        "7":{"wins":0,"losses":0},
        "8":{"wins":0,"losses":0}
    },
    "[null,\"X\",null,null,null,\"O\",null,null,null]":{
        "0":{"wins":0,"losses":0},
        "2":{"wins":0,"losses":0},
        "3":{"wins":0,"losses":0},
        "4":{"wins":0,"losses":0},
        "6":{"wins":0,"losses":0},
        "7":{"wins":0,"losses":0},
        "8":{"wins":0,"losses":0}
    },
    "[null,null,null,null,null,null,null,null,null]":{
        "0":{"wins":0,"losses":0},
        "1":{"wins":0,"losses":0},
        "2":{"wins":0,"losses":0},
        "3":{"wins":0,"losses":0},
        "4":{"wins":0,"losses":0},
        "5":{"wins":0,"losses":0},
        "6":{"wins":0,"losses":0},
        "7":{"wins":0,"losses":0},
        "8":{"wins":0,"losses":0}
    },
    "[\"X\",null,null,null,\"O\",\"O\",null,null,\"X\"]":{
        "1":{"wins":0,"losses":0},
        "2":{"wins":0,"losses":0},
        "3":{"wins":0,"losses":0},
        "6":{"wins":0,"losses":0},
        "7":{"wins":0,"losses":0}
    },
    "[\"X\",null,\"O\",null,\"O\",null,\"X\",null,null]":{
        "1":{"wins":0,"losses":0},
        "3":{"wins":0,"losses":0},
        "5":{"wins":0,"losses":0},
        "7":{"wins":0,"losses":0},
        "8":{"wins":0,"losses":0}
    }
    
}